setup.py
Cyclic_Voltammogram.egg-info/PKG-INFO
Cyclic_Voltammogram.egg-info/SOURCES.txt
Cyclic_Voltammogram.egg-info/dependency_links.txt
Cyclic_Voltammogram.egg-info/not-zip-safe
Cyclic_Voltammogram.egg-info/top_level.txt
voltammogram/DuckPeaks.py
voltammogram/Generalvoltammogram.py
voltammogram/__init__.py