Metadata-Version: 1.0
Name: Cyclic-Voltammogram
Version: 0.4
Summary: Determine Peaks of Cyclic Voltammogram
Home-page: UNKNOWN
Author: UNKNOWN
Author-email: UNKNOWN
License: UNKNOWN
Platform: UNKNOWN
